archetyper-1.2.2.dist-info/licenses/LICENSE
archetypes/__init__.py
archetypes/archetypes.py
archetyper-1.2.2.dist-info/METADATA
archetyper-1.2.2.dist-info/WHEEL
archetyper-1.2.2.dist-info/top_level.txt
archetyper-1.2.2.dist-info/RECORD
