Metadata-Version: 2.4
Name: archetyper
Version: 1.2.2
Summary: Create and quantify 'archetypes' of your constructs. A dictionary-like method run amok!
Author-email: "Ryan L. Boyd" <ryan@ryanboyd.io>, Vasudha Varadarajan <vvaradarajan@cs.stonybrook.edu>, Sid Mangalik <smangalik@cs.stonybrook.edu>
Project-URL: Homepage, https://github.com/ryanboyd/archetypes
Project-URL: Issues, https://github.com/ryanboyd/archetypes/issues
Classifier: Programming Language :: Python :: 3
Classifier: License :: OSI Approved :: MIT License
Classifier: Operating System :: OS Independent
Requires-Python: >=3.8
License-File: LICENSE
Requires-Dist: numpy>=1.25.2
Requires-Dist: tqdm>=4.66.1
Requires-Dist: torch>=2.0.1
Requires-Dist: sentence_transformers>=3.1.1
Requires-Dist: nltk>=3.8.1
Dynamic: license-file
